MANIFEST.in
licence.txt
readme.md
setup.py
keopscore/__init__.py
keopscore/get_keops_dll.py
keopscore/keops_version
keopscore/licence.txt
keopscore/readme.md
keopscore.egg-info/PKG-INFO
keopscore.egg-info/SOURCES.txt
keopscore.egg-info/dependency_links.txt
keopscore.egg-info/top_level.txt
keopscore/binders/LinkCompile.py
keopscore/binders/__init__.py
keopscore/binders/cpp/Cpu_link_compile.py
keopscore/binders/cpp/__init__.py
keopscore/binders/nvrtc/Gpu_link_compile.py
keopscore/binders/nvrtc/__init__.py
keopscore/binders/nvrtc/keops_nvrtc.cpp
keopscore/binders/nvrtc/nvrtc_jit.cpp
keopscore/config/Platform.py
keopscore/config/__init__.py
keopscore/config/base_config.py
keopscore/config/chunks.py
keopscore/config/cuda.py
keopscore/config/openmp.py
keopscore/formulas/Chunkable_Op.py
keopscore/formulas/GetReduction.py
keopscore/formulas/Operation.py
keopscore/formulas/VectorizedComplexScalarOp.py
keopscore/formulas/VectorizedScalarOp.py
keopscore/formulas/__init__.py
keopscore/formulas/checks.py
keopscore/formulas/LinearOperators/AdjointOperator.py
keopscore/formulas/LinearOperators/LinearOperator.py
keopscore/formulas/LinearOperators/SumLinOperator.py
keopscore/formulas/LinearOperators/TraceOperator.py
keopscore/formulas/LinearOperators/__init__.py
keopscore/formulas/autodiff/Diff.py
keopscore/formulas/autodiff/Diff_WithSavedForward.py
keopscore/formulas/autodiff/Divergence.py
keopscore/formulas/autodiff/Grad.py
keopscore/formulas/autodiff/Grad_WithSavedForward.py
keopscore/formulas/autodiff/Laplacian.py
keopscore/formulas/autodiff/__init__.py
keopscore/formulas/complex/ComplexAbs.py
keopscore/formulas/complex/ComplexAdd.py
keopscore/formulas/complex/ComplexAngle.py
keopscore/formulas/complex/ComplexDivide.py
keopscore/formulas/complex/ComplexExp.py
keopscore/formulas/complex/ComplexExp1j.py
keopscore/formulas/complex/ComplexImag.py
keopscore/formulas/complex/ComplexMult.py
keopscore/formulas/complex/ComplexReal.py
keopscore/formulas/complex/ComplexRealScal.py
keopscore/formulas/complex/ComplexSquareAbs.py
keopscore/formulas/complex/ComplexSubtract.py
keopscore/formulas/complex/ComplexSum.py
