Metadata-Version: 2.4
Name: keopscore
Version: 2.3
Summary: keopscore is the KeOps meta programming engine. This python module should be used through a binder (e.g. pykeops or rkeops)
Home-page: http://www.kernel-operations.io/
Author: B. Charlier, J. Feydy, J. Glaunes
Author-email: benjamin.charlier@umontpellier.fr, jean.feydy@gmail.com, alexis.glaunes@parisdescartes.fr
Project-URL: Bug Reports, https://github.com/getkeops/keops/issues
Project-URL: Source, https://github.com/getkeops/keops
Keywords: kernels gpu autodiff
Classifier: Development Status :: 5 - Production/Stable
Classifier: Intended Audience :: Developers
Classifier: Topic :: Scientific/Engineering
Classifier: License :: OSI Approved :: MIT License
Classifier: Operating System :: POSIX :: Linux
Classifier: Operating System :: MacOS :: MacOS X
Classifier: Programming Language :: C++
Classifier: Programming Language :: Python :: 3 :: Only
Requires-Python: >=3.8
Dynamic: author
Dynamic: author-email
Dynamic: classifier
Dynamic: description
Dynamic: description-content-type
Dynamic: home-page
Dynamic: keywords
Dynamic: project-url
Dynamic: requires-python
Dynamic: summary
